spotflow/__init__.py
spotflow/__main__.py
spotflow/api.py
spotflow/cmdline.py
spotflow/collector.py
spotflow/info.py
spotflow/model.py
spotflow/report.py
spotflow/report_csv.py
spotflow/report_html.py
spotflow/report_pprint.py
spotflow/sample.py
spotflow/tracer.py
spotflow/utils.py
spotflow/utils_pytest.py
spotflow/utils_unittest.py
spotflow/htmlfiles/coverage_html.js
spotflow/htmlfiles/highlight.css
spotflow/htmlfiles/index.html
spotflow/htmlfiles/pyfile2.html
spotflow/htmlfiles/style.css
spotflow/libs/__init__.py
spotflow/libs/templite.py
spotflow-1.1.0.dist-info/METADATA
spotflow-1.1.0.dist-info/WHEEL
spotflow-1.1.0.dist-info/licenses/LICENSE
spotflow-1.1.0.dist-info/RECORD
