Metadata-Version: 2.1
Name: spotflow
Version: 1.1.0
Summary: Runtime analysis for Python programs
Project-URL: Homepage, https://github.com/andrehora/spotflow
Project-URL: Bug Tracker, https://github.com/andrehora/spotflow/issues
Author-email: Andre Hora <andrehoraa@gmail.com>
License-File: LICENSE
Keywords: dynamic-analysis,testing
Classifier: Intended Audience :: Developers
Classifier: License :: OSI Approved :: MIT License
Classifier: Operating System :: OS Independent
Classifier: Programming Language :: Python :: 3
Classifier: Programming Language :: Python :: 3.7
Classifier: Programming Language :: Python :: 3.8
Classifier: Programming Language :: Python :: 3.9
Classifier: Programming Language :: Python :: 3.10
Classifier: Topic :: Software Development :: Quality Assurance
Classifier: Topic :: Software Development :: Testing
Requires-Python: >=3.7
Requires-Dist: coverage==6.5.0
Requires-Dist: pygments
Requires-Dist: pytest
